pytest_doctestplus/__init__.py
pytest_doctestplus/newhooks.py
pytest_doctestplus/output_checker.py
pytest_doctestplus/plugin.py
pytest_doctestplus/utils.py
pytest_doctestplus/version.py
pytest_doctestplus/sphinx/__init__.py
pytest_doctestplus/sphinx/doctestplus.py
pytest_doctestplus-1.7.0.dist-info/licenses/LICENSE.rst
pytest_doctestplus-1.7.0.dist-info/METADATA
pytest_doctestplus-1.7.0.dist-info/WHEEL
pytest_doctestplus-1.7.0.dist-info/entry_points.txt
pytest_doctestplus-1.7.0.dist-info/top_level.txt
pytest_doctestplus-1.7.0.dist-info/RECORD
