Metadata-Version: 2.4
Name: pytest-doctestplus
Version: 1.7.0
Summary: Pytest plugin with advanced doctest features.
Home-page: https://github.com/scientific-python/pytest-doctestplus
Author: Scientific Python Developers
License: BSD
Keywords: doctest,rst,pytest,py.test
Classifier: Development Status :: 5 - Production/Stable
Classifier: Framework :: Pytest
Classifier: Intended Audience :: Developers
Classifier: License :: OSI Approved :: BSD License
Classifier: Operating System :: OS Independent
Classifier: Programming Language :: Python
Classifier: Programming Language :: Python :: 3
Classifier: Programming Language :: Python :: 3 :: Only
Classifier: Programming Language :: Python :: 3.10
Classifier: Programming Language :: Python :: 3.11
Classifier: Programming Language :: Python :: 3.12
Classifier: Programming Language :: Python :: 3.13
Classifier: Programming Language :: Python :: 3.14
Classifier: Programming Language :: Python :: Implementation :: CPython
Classifier: Topic :: Software Development :: Testing
Classifier: Topic :: Utilities
Requires-Python: >=3.10
License-File: LICENSE.rst
Requires-Dist: pytest>=7.0
Requires-Dist: packaging>=17.0
Provides-Extra: test
Requires-Dist: numpy; extra == "test"
Requires-Dist: pytest-remotedata>=0.3.2; extra == "test"
Requires-Dist: setuptools>=30.3.0; extra == "test"
Requires-Dist: sphinx; extra == "test"
Dynamic: license-file
